tinyantigate.py
tinyantigate-0.1.1.dist-info/DESCRIPTION.rst
tinyantigate-0.1.1.dist-info/METADATA
tinyantigate-0.1.1.dist-info/RECORD
tinyantigate-0.1.1.dist-info/WHEEL
tinyantigate-0.1.1.dist-info/metadata.json
tinyantigate-0.1.1.dist-info/top_level.txt
