Metadata-Version: 2.0
Name: tinyantigate
Version: 0.1.1
Summary: Tiny antigate/anti-captcha api wrapper.
Home-page: https://github.com/pohmelie/tinyantigate
Author: pohmelie
Author-email: multisosnooley@gmail.com
License: WTFPL
Platform: UNKNOWN
Classifier: Programming Language :: Python
Classifier: Programming Language :: Python :: 3
Requires-Dist: requests
